ttok/__init__.py
ttok/__main__.py
ttok/cli.py
ttok-0.3.dist-info/LICENSE
ttok-0.3.dist-info/METADATA
ttok-0.3.dist-info/WHEEL
ttok-0.3.dist-info/entry_points.txt
ttok-0.3.dist-info/top_level.txt
ttok-0.3.dist-info/RECORD
