Metadata-Version: 2.1
Name: ttok
Version: 0.3
Summary: Count and truncate text based on tokens
Home-page: https://github.com/simonw/ttok
Author: Simon Willison
License: Apache License, Version 2.0
Project-URL: Issues, https://github.com/simonw/ttok/issues
Project-URL: CI, https://github.com/simonw/ttok/actions
Project-URL: Changelog, https://github.com/simonw/ttok/releases
Requires-Python: >=3.8
License-File: LICENSE
Requires-Dist: click
Requires-Dist: tiktoken
Provides-Extra: test
Requires-Dist: pytest ; extra == 'test'
Requires-Dist: cogapp ; extra == 'test'
